{
  "metadata": {
    "total_students": 36,
    "evaluation_date": "2025-12-23",
    "total_criteria": 30
  },
  "criteria": {
    "Error Handling": {
      "display_name": "Error Handling",
      "students": [
        "38950",
        "38951",
        "38952",
        "38953",
        "38954",
        "38955",
        "38958",
        "38959",
        "38960",
        "38962",
        "38963",
        "38964",
        "38966",
        "38970",
        "38971",
        "38973",
        "38977",
        "38979",
        "38980",
        "38981",
        "38982",
        "38984",
        "38985",
        "38986",
        "38988",
        "38989",
        "38990",
        "38992",
        "38993",
        "59373",
        "59375",
        "59378"
      ],
      "count": 32,
      "weight": 0.8888888888888888
    },
    "PRD Document": {
      "display_name": "PRD Document",
      "students": [
        "38950",
        "38951",
        "38952",
        "38953",
        "38954",
        "38955",
        "38958",
        "38959",
        "38960",
        "38962",
        "38963",
        "38964",
        "38970",
        "38977",
        "38979",
        "38980",
        "38981",
        "38982",
        "38984",
        "38986",
        "38988",
        "38989",
        "38990",
        "38992",
        "38993",
        "59373",
        "59375",
        "59378"
      ],
      "count": 28,
      "weight": 0.7777777777777778
    },
    "Comparative Analysis": {
      "display_name": "Comparative Analysis",
      "students": [
        "38950",
        "38951",
        "38952",
        "38953",
        "38954",
        "38955",
        "38959",
        "38960",
        "38964",
        "38970",
        "38979",
        "38980",
        "38981",
        "38982",
        "38988",
        "38989",
        "38993",
        "59375",
        "59378"
      ],
      "count": 19,
      "weight": 0.5277777777777778
    },
    "Test Coverage Metrics": {
      "display_name": "Test Coverage Metrics",
      "students": [
        "38950",
        "38951",
        "38952",
        "38953",
        "38954",
        "38955",
        "38958",
        "38959",
        "38960",
        "38962",
        "38964",
        "38969",
        "38970",
        "38971",
        "38973",
        "38977",
        "38979",
        "38980",
        "38981",
        "38982",
        "38984",
        "38986",
        "38988",
        "38989",
        "38990",
        "38992",
        "38993",
        "59373",
        "59375",
        "59376",
        "59378"
      ],
      "count": 31,
      "weight": 0.8611111111111112
    },
    "E2E Tests": {
      "display_name": "E2E Tests",
      "students": [
        "38950",
        "38954",
        "38958",
        "38964",
        "38979",
        "38980"
      ],
      "count": 6,
      "weight": 0.16666666666666666
    },
    "Data Validation": {
      "display_name": "Data Validation",
      "students": [
        "38950",
        "38951",
        "38952",
        "38953",
        "38954",
        "38955",
        "38958",
        "38959",
        "38960",
        "38962",
        "38963",
        "38964",
        "38969",
        "38970",
        "38971",
        "38973",
        "38977",
        "38979",
        "38980",
        "38981",
        "38982",
        "38984",
        "38988",
        "38989",
        "38990",
        "38993",
        "59373",
        "59375",
        "59376",
        "59378"
      ],
      "count": 30,
      "weight": 0.8333333333333334
    },
    "Unit Tests": {
      "display_name": "Unit Tests",
      "students": [
        "38950",
        "38951",
        "38952",
        "38953",
        "38954",
        "38955",
        "38957",
        "38958",
        "38959",
        "38960",
        "38961",
        "38962",
        "38963",
        "38964",
        "38966",
        "38969",
        "38970",
        "38971",
        "38973",
        "38977",
        "38979",
        "38980",
        "38981",
        "38982",
        "38984",
        "38985",
        "38986",
        "38988",
        "38989",
        "38990",
        "38992",
        "38993",
        "59373",
        "59375",
        "59376",
        "59378"
      ],
      "count": 36,
      "weight": 1.0
    },
    "Installation Instructions": {
      "display_name": "Installation Instructions",
      "students": [
        "38950",
        "38951",
        "38954",
        "38955",
        "38958",
        "38959",
        "38962",
        "38964",
        "38969",
        "38977",
        "38979",
        "38980",
        "38981",
        "38984",
        "38986",
        "38990",
        "38992",
        "59375",
        "59376",
        "59378"
      ],
      "count": 20,
      "weight": 0.5555555555555556
    },
    "Configuration Management": {
      "display_name": "Configuration Management",
      "students": [
        "38950",
        "38951",
        "38952",
        "38953",
        "38954",
        "38955",
        "38957",
        "38958",
        "38959",
        "38960",
        "38961",
        "38962",
        "38963",
        "38964",
        "38966",
        "38969",
        "38970",
        "38971",
        "38973",
        "38977",
        "38979",
        "38980",
        "38981",
        "38982",
        "38984",
        "38985",
        "38986",
        "38988",
        "38989",
        "38990",
        "38992",
        "38993",
        "59373",
        "59375",
        "59376",
        "59378"
      ],
      "count": 36,
      "weight": 1.0
    },
    "Usage Guide": {
      "display_name": "Usage Guide",
      "students": [
        "38951",
        "38953",
        "38954",
        "38955",
        "38960",
        "38962",
        "38963",
        "38964",
        "38969",
        "38970",
        "38971",
        "38973",
        "38977",
        "38979",
        "38980",
        "38981",
        "38984",
        "38988",
        "38989",
        "38990",
        "59376",
        "59378"
      ],
      "count": 22,
      "weight": 0.6111111111111112
    },
    "Testing Documentation": {
      "display_name": "Testing Documentation",
      "students": [
        "38951",
        "38952",
        "38954",
        "38955",
        "38959",
        "38962",
        "38963",
        "38964",
        "38969",
        "38977",
        "38979",
        "38980",
        "38981",
        "38982",
        "38984",
        "38986",
        "38990",
        "38992",
        "38993",
        "59373",
        "59375",
        "59376",
        "59378"
      ],
      "count": 23,
      "weight": 0.6388888888888888
    },
    "Statistical Analysis": {
      "display_name": "Statistical Analysis",
      "students": [
        "38951",
        "38954",
        "38959",
        "38960",
        "38962",
        "38963",
        "38964",
        "38966",
        "38969",
        "38970",
        "38971",
        "38977",
        "38979",
        "38980",
        "38981",
        "59375",
        "59378"
      ],
      "count": 17,
      "weight": 0.4722222222222222
    },
    "Quick Start Guide": {
      "display_name": "Quick Start Guide",
      "students": [
        "38951",
        "38952",
        "38954",
        "38955",
        "38962",
        "38964",
        "38977",
        "38986",
        "38992",
        "59373"
      ],
      "count": 10,
      "weight": 0.2777777777777778
    },
    "Multi-Stage Pipeline": {
      "display_name": "Multi-Stage Pipeline",
      "students": [
        "38951",
        "38954",
        "38962",
        "38964",
        "38977"
      ],
      "count": 5,
      "weight": 0.1388888888888889
    },
    "Visualizations": {
      "display_name": "Visualizations",
      "students": [
        "38951",
        "38954",
        "38962",
        "38964",
        "38977",
        "38979",
        "38980",
        "38981",
        "59378"
      ],
      "count": 9,
      "weight": 0.25
    },
    "Architecture Documentation": {
      "display_name": "Architecture Documentation",
      "students": [
        "38951",
        "38952",
        "38953",
        "38954",
        "38959",
        "38960",
        "38962",
        "38964",
        "38969",
        "38970",
        "38977",
        "38979",
        "38980",
        "38982",
        "38988",
        "38989",
        "38993",
        "59373",
        "59375",
        "59376"
      ],
      "count": 20,
      "weight": 0.5555555555555556
    },
    "Correlation Analysis": {
      "display_name": "Correlation Analysis",
      "students": [
        "38951",
        "38954",
        "38962",
        "38964",
        "38977",
        "38979",
        "38980",
        "38981",
        "59378"
      ],
      "count": 9,
      "weight": 0.25
    },
    "Integration Tests": {
      "display_name": "Integration Tests",
      "students": [
        "38951",
        "38954",
        "38964",
        "38981",
        "38986",
        "38992",
        "59378"
      ],
      "count": 7,
      "weight": 0.19444444444444445
    },
    "Performance Benchmarking": {
      "display_name": "Performance Benchmarking",
      "students": [
        "38952",
        "38953",
        "38954",
        "38962",
        "38964",
        "38977",
        "38979",
        "38980",
        "38984",
        "38986",
        "38988",
        "38989",
        "38990",
        "38992",
        "59373"
      ],
      "count": 15,
      "weight": 0.4166666666666667
    },
    "Contributing Guide": {
      "display_name": "Contributing Guide",
      "students": [
        "38952",
        "38955",
        "38960",
        "38962",
        "38963",
        "38969",
        "38970",
        "38977",
        "38979",
        "38980",
        "38981",
        "38986",
        "38992",
        "59373",
        "59376",
        "59378"
      ],
      "count": 16,
      "weight": 0.4444444444444444
    },
    "Setup Guide": {
      "display_name": "Setup Guide",
      "students": [
        "38952",
        "38953",
        "38954",
        "38960",
        "38962",
        "38964",
        "38969",
        "38970",
        "38977",
        "38981",
        "38988",
        "38989",
        "59373",
        "59376",
        "59378"
      ],
      "count": 15,
      "weight": 0.4166666666666667
    },
    "Changelog": {
      "display_name": "Changelog",
      "students": [
        "38952",
        "38960",
        "38970",
        "38979",
        "38980",
        "59373"
      ],
      "count": 6,
      "weight": 0.16666666666666666
    },
    "Jupyter Notebooks": {
      "display_name": "Jupyter Notebooks",
      "students": [
        "38954",
        "38959",
        "38960",
        "38979",
        "38981",
        "38982",
        "38993",
        "59375"
      ],
      "count": 8,
      "weight": 0.2222222222222222
    },
    "Deployment Guide": {
      "display_name": "Deployment Guide",
      "students": [
        "38954",
        "38960",
        "38964",
        "38970",
        "38979",
        "38980"
      ],
      "count": 6,
      "weight": 0.16666666666666666
    },
    "Results Documentation": {
      "display_name": "Results Documentation",
      "students": [
        "38954",
        "38955",
        "38962",
        "38964",
        "38977",
        "38981",
        "59378"
      ],
      "count": 7,
      "weight": 0.19444444444444445
    },
    "API Documentation": {
      "display_name": "API Documentation",
      "students": [
        "38954",
        "38964",
        "38979",
        "38980"
      ],
      "count": 4,
      "weight": 0.1111111111111111
    },
    "DevOps Documentation": {
      "display_name": "DevOps Documentation",
      "students": [
        "38954",
        "38959",
        "38964",
        "38979",
        "38980",
        "59375"
      ],
      "count": 6,
      "weight": 0.16666666666666666
    },
    "Screenshots": {
      "display_name": "Screenshots",
      "students": [
        "38954",
        "38955",
        "38960",
        "38962",
        "38963",
        "38964",
        "38970",
        "38977",
        "38979",
        "38980",
        "38981",
        "59378"
      ],
      "count": 12,
      "weight": 0.3333333333333333
    },
    "Methodology Documentation": {
      "display_name": "Methodology Documentation",
      "students": [
        "38959",
        "38982",
        "38993",
        "59375"
      ],
      "count": 4,
      "weight": 0.1111111111111111
    },
    "Use Cases Documentation": {
      "display_name": "Use Cases Documentation",
      "students": [
        "38981",
        "59378"
      ],
      "count": 2,
      "weight": 0.05555555555555555
    }
  }
}